LICENSE
README.md
setup.py
DeepCell_Tracking.egg-info/PKG-INFO
DeepCell_Tracking.egg-info/SOURCES.txt
DeepCell_Tracking.egg-info/dependency_links.txt
DeepCell_Tracking.egg-info/requires.txt
DeepCell_Tracking.egg-info/top_level.txt
deepcell_tracking/__init__.py
deepcell_tracking/isbi_utils.py
deepcell_tracking/isbi_utils_test.py
deepcell_tracking/metrics.py
deepcell_tracking/metrics_test.py
deepcell_tracking/test_utils.py
deepcell_tracking/tracking.py
deepcell_tracking/tracking_test.py
deepcell_tracking/trk_io.py
deepcell_tracking/trk_io_test.py
deepcell_tracking/utils.py
deepcell_tracking/utils_test.py