Metadata-Version: 2.1
Name: DeepCell-Tracking
Version: 0.6.1
Summary: Tracking cells and lineage with deep learning.
Home-page: https://github.com/vanvalenlab/deepcell-tracking
Author: Van Valen Lab
Author-email: vanvalenlab@gmail.com
License: LICENSE
Download-URL: https://github.com/vanvalenlab/deepcell-tracking/tarball/0.6.1
Platform: UNKNOWN
Classifier: Programming Language :: Python
Classifier: Programming Language :: Python :: 3
Classifier: Programming Language :: Python :: 3.7
Classifier: Programming Language :: Python :: 3.8
Classifier: Programming Language :: Python :: 3.9
Provides-Extra: tests
License-File: LICENSE
